setup.py
thehulk/__init__.py
thehulk/turn.py
thehulk.egg-info/PKG-INFO
thehulk.egg-info/SOURCES.txt
thehulk.egg-info/dependency_links.txt
thehulk.egg-info/not-zip-safe
thehulk.egg-info/top_level.txt