Metadata-Version: 1.0
Name: thehulk
Version: 0.1.1
Summary: smash!
Home-page: https://github.com/wrecodde/thehulk
Author: deji joseph
Author-email: wrecodde@gmail.com
License: UNKNOWN
Platform: UNKNOWN
